rft1d/__init__.py
rft1d/data.py
rft1d/distributions.py
rft1d/geom.py
rft1d/prob.py
rft1d/random.py
rft1d/data/weather/README.txt
rft1d/data/weather/daily.m
rft1d/data/weather/daily.mat
rft1d-0.2.5.dist-info/licenses/LICENSE.txt
rft1d-0.2.5.dist-info/METADATA
rft1d-0.2.5.dist-info/WHEEL
rft1d-0.2.5.dist-info/top_level.txt
rft1d-0.2.5.dist-info/RECORD
