Metadata-Version: 2.4
Name: rft1d
Version: 0.2.5
Summary: 'One-Dimensional Random Field Theory
Author-email: Todd Pataky <0todd0@gmail.com>
Project-URL: Homepage, https://www.spm1d.org/rft1d
Project-URL: Source, https://github.com/0todd0000/rft1d
Project-URL: Bug Reports, https://github.com/0todd0000/rft1d/issues
Keywords: statistics,probability,hypothesis testing,functional data analysis,time series analysis,continuum data analysis
Classifier: Development Status :: 4 - Beta
Classifier: License :: OSI Approved :: GNU General Public License v3 (GPLv3)
Classifier: Topic :: Scientific/Engineering
Classifier: Programming Language :: Python :: 3.9
Requires-Python: >=3.7
License-File: LICENSE.txt
Requires-Dist: numpy
Requires-Dist: scipy
Requires-Dist: matplotlib
Dynamic: license-file
